nonebot_plugin_alconna-0.60.4.dist-info/METADATA
nonebot_plugin_alconna-0.60.4.dist-info/WHEEL
nonebot_plugin_alconna-0.60.4.dist-info/entry_points.txt
nonebot_plugin_alconna-0.60.4.dist-info/licenses/LICENSE
nonebot_plugin_alconna/__init__.py
nonebot_plugin_alconna/argv.py
nonebot_plugin_alconna/builtins/extensions/__init__.py
nonebot_plugin_alconna/builtins/extensions/discord.py
nonebot_plugin_alconna/builtins/extensions/markdown.py
nonebot_plugin_alconna/builtins/extensions/onebot11.py
nonebot_plugin_alconna/builtins/extensions/permission.py
nonebot_plugin_alconna/builtins/extensions/reply.py
nonebot_plugin_alconna/builtins/extensions/shortcut.py
nonebot_plugin_alconna/builtins/extensions/telegram.py
nonebot_plugin_alconna/builtins/plugins/__init__.py
nonebot_plugin_alconna/builtins/plugins/echo/__init__.py
nonebot_plugin_alconna/builtins/plugins/echo/config.py
nonebot_plugin_alconna/builtins/plugins/help/__init__.py
nonebot_plugin_alconna/builtins/plugins/help/config.py
nonebot_plugin_alconna/builtins/plugins/lang.py
nonebot_plugin_alconna/builtins/plugins/switch/__init__.py
nonebot_plugin_alconna/builtins/plugins/switch/config.py
nonebot_plugin_alconna/builtins/plugins/with/__init__.py
nonebot_plugin_alconna/builtins/plugins/with/config.py
nonebot_plugin_alconna/builtins/plugins/with/extension.py
nonebot_plugin_alconna/builtins/uniseg/__init__.py
nonebot_plugin_alconna/builtins/uniseg/markdown.py
nonebot_plugin_alconna/builtins/uniseg/market_face.py
nonebot_plugin_alconna/builtins/uniseg/music_share.py
nonebot_plugin_alconna/config.py
nonebot_plugin_alconna/consts.py
nonebot_plugin_alconna/extension.py
nonebot_plugin_alconna/i18n/.config.json
nonebot_plugin_alconna/i18n/.lang.schema.json
nonebot_plugin_alconna/i18n/.template.json
nonebot_plugin_alconna/i18n/.template.schema.json
nonebot_plugin_alconna/i18n/__init__.py
nonebot_plugin_alconna/i18n/en-US.json
nonebot_plugin_alconna/i18n/model.py
nonebot_plugin_alconna/i18n/zh-CN.json
nonebot_plugin_alconna/matcher.py
nonebot_plugin_alconna/model.py
nonebot_plugin_alconna/params.py
nonebot_plugin_alconna/pattern.py
nonebot_plugin_alconna/py.typed
nonebot_plugin_alconna/rule.py
nonebot_plugin_alconna/shortcut.py
nonebot_plugin_alconna-0.60.4.dist-info/RECORD
