Metadata-Version: 2.1
Name: nonebot-plugin-alconna
Version: 0.60.4
Summary: Alconna Adapter for Nonebot
Keywords: command,alconna,nonebot
Author-Email: RF-Tar-Railt <rf_tar_railt@qq.com>
License: MIT
Project-URL: homepage, https://github.com/nonebot/plugin-alconna
Project-URL: repository, https://github.com/nonebot/plugin-alconna
Requires-Python: >=3.10
Requires-Dist: tarina<0.8.0,>=0.7.3
Requires-Dist: nepattern<1.0,>=0.7.7
Requires-Dist: arclet-alconna<2.0,>=1.8.43
Requires-Dist: arclet-alconna-tools>=0.7.12
Requires-Dist: importlib-metadata>=8.7.0
Requires-Dist: nonebot2>=2.4.3
Requires-Dist: nonebot-plugin-waiter>=0.8.1
